MANIFEST.in
README.md
README.txt
hcss.py
hcss_tests.py
setup.py
examples/element-based-complex-rules/element-based-complex-rules.css
examples/element-based-complex-rules/element-based-complex-rules.hcss
examples/element-based-simple-rules/element-based-simple-rules.css
examples/element-based-simple-rules/element-based-simple-rules.hcss
examples/inheritance/inheritance.css
examples/inheritance/inheritance.hcss
examples/standalone-and-element-based-rules/standalone-and-element-based-rules.css
examples/standalone-and-element-based-rules/standalone-and-element-based-rules.hcss
hcss.egg-info/PKG-INFO
hcss.egg-info/SOURCES.txt
hcss.egg-info/dependency_links.txt
hcss.egg-info/entry_points.txt
hcss.egg-info/top_level.txt