Metadata-Version: 1.0
Name: hcss
Version: 0.2
Summary: hcss is a CSS compiler that that allows you to use HTML element hierarchy to define CSS rules
Home-page: http://jonasgalvez.com.br/Software/HCSS.html
Author: Jonas Galvez
Author-email: jonasgalvez@gmail.com
License: BSD
Platform: Python 2.5 and later
Classifier: Intended Audience :: Developers
Classifier: Development Status :: 4 - Beta
Classifier: License :: OSI Approved :: BSD License
Classifier: Operating System :: OS Independent
Classifier: Programming Language :: Python
Classifier: Topic :: Software Development :: Compilers
Classifier: Topic :: Software Development :: User Interfaces
Classifier: Topic :: Text Processing :: Markup :: HTML
